datasurface/__init__.py
datasurface/__init__.pyi
datasurface/py.typed
datasurface/cmd/platform.py
datasurface/codegen/CodeGen.py
datasurface/codegen/__init__.py
datasurface/codegen/__init__.pyi
datasurface/codegen/templates/__init__.py
datasurface/codegen/templates/datastore.jinja2
datasurface/handler/__init__.py
datasurface/handler/__init__.pyi
datasurface/handler/action.py
datasurface/handler/action.pyi
datasurface/handler/check-files-changed.yml
datasurface/handler/cicd.py
datasurface/handler/cicd.pyi
datasurface/handler/pull-request.yml
datasurface/md/__init__.py
datasurface/md/__init__.pyi
datasurface/md/avroschema.py
datasurface/md/codeartifact.py
datasurface/md/credential.py
datasurface/md/documentation.py
datasurface/md/equality_enforcer.py
datasurface/md/exceptions.py
datasurface/md/governance.py
datasurface/md/json.py
datasurface/md/keys.py
datasurface/md/lint.py
datasurface/md/model_loader.py
datasurface/md/model_schema.py
datasurface/md/policy.py
datasurface/md/repo.py
datasurface/md/schema.py
datasurface/md/security.py
datasurface/md/server.py
datasurface/md/sqlalchemyutils.py
datasurface/md/types.py
datasurface/md/utils.py
datasurface/md/vendor.py
datasurface/md/datacontainers/__init__.py
datasurface/platforms/__init__.py
datasurface/platforms/__init__.pyi
datasurface/platforms/common/README.md
datasurface/platforms/common/__init__.py
datasurface/platforms/common/graphsql.py
datasurface/platforms/common/broker_render/__init__.py
datasurface/platforms/legacy/README.md
datasurface/platforms/legacy/__init__.py
datasurface/platforms/legacy/legacy.py
datasurface/platforms/yellow/__init__.py
datasurface/platforms/yellow/assembly.py
datasurface/platforms/yellow/aws_assembly.py
datasurface/platforms/yellow/data_ops_db2.py
datasurface/platforms/yellow/data_ops_factory.py
datasurface/platforms/yellow/data_ops_oracle.py
datasurface/platforms/yellow/data_ops_postgres.py
datasurface/platforms/yellow/data_ops_snowflake.py
datasurface-0.1.2.dist-info/licenses/LICENSE.txt
datasurface-0.1.2.dist-info/METADATA
datasurface-0.1.2.dist-info/WHEEL
datasurface-0.1.2.dist-info/top_level.txt
datasurface-0.1.2.dist-info/RECORD
