Metadata-Version: 2.4
Name: datasurface
Version: 0.1.2
Summary: Automate the governance, management and movement of data within your enterprise
Home-page: https://github.com/billynewport/datasurface
Author: Billy Newport
Author-email: billy@datasurface.com
License: BSL_v1.1
Classifier: License :: Other/Proprietary License
Classifier: Development Status :: 3 - Alpha
Classifier: Intended Audience :: Developers
Classifier: Intended Audience :: Information Technology
Classifier: Natural Language :: English
Classifier: Programming Language :: Python :: 3.13
Classifier: Topic :: Database :: Database Engines/Servers
Requires-Python: >=3.13
License-File: LICENSE.txt
Requires-Dist: Jinja2==3.1.6
Requires-Dist: psycopg2-binary==2.9.10
Requires-Dist: pycountry==23.12.11
Requires-Dist: pytest==8.3.3
Requires-Dist: python-dateutil==2.8.2
Requires-Dist: SQLAlchemy==2.0.41
Requires-Dist: types-python-dateutil==2.8.19.20240106
Requires-Dist: typing_extensions==4.12.2
Requires-Dist: PyGithub==2.2.0
Requires-Dist: avro==1.12.0
Requires-Dist: urllib3==2.5.0
Requires-Dist: pyyaml==6.0.2
Requires-Dist: fastapi==0.115.12
Requires-Dist: pydantic==2.11.2
Requires-Dist: slack_sdk==3.35.0
Requires-Dist: httpx==0.28.1
Requires-Dist: ibm_db>=3.2.6
Requires-Dist: ibm-db-sa>=0.4.2
Requires-Dist: oracledb>=1.4.0
Requires-Dist: pymysql>=1.0.2
Requires-Dist: pyodbc>=4.0.34
Requires-Dist: geoalchemy2==0.18.0
Requires-Dist: snowflake-sqlalchemy==1.7.6
Requires-Dist: snowflake-connector-python==3.17.2
Requires-Dist: boto3==1.40.19
Dynamic: author
Dynamic: author-email
Dynamic: classifier
Dynamic: description
Dynamic: description-content-type
Dynamic: home-page
Dynamic: license
Dynamic: license-file
Dynamic: requires-dist
Dynamic: requires-python
Dynamic: summary
